LICENSE.txt
MANIFEST.in
README.md
README.rst
requirements.txt
setup.py
pug/__init__.py
pug/data/__init__.py
pug/data/__init__.pyc
pug/invest/__init__.py
pug/invest/models.py
pug/invest/package_info.py
pug/invest/plot.py
pug/invest/tests.py
pug/invest/urls.py
pug/invest/util.py
pug/invest/views.py
pug_invest.egg-info/PKG-INFO
pug_invest.egg-info/SOURCES.txt
pug_invest.egg-info/dependency_links.txt
pug_invest.egg-info/namespace_packages.txt
pug_invest.egg-info/requires.txt
pug_invest.egg-info/top_level.txt