Metadata-Version: 1.1
Name: pug-invest
Version: 0.0.18
Summary: # pug-invest
Home-page: UNKNOWN
Author: Hobson <hobson@totalgood.com>
Author-email: hobson@totalgood.com
License: UNKNOWN
Download-URL: https://github.com/hobson/pug-invest/tarball/master
Keywords: finance,quant,quantitative finance,time series,analysis,data,science,data science,math,machine-learning,statistics
Platform: UNKNOWN
Classifier: Programming Language :: Python
Classifier: Programming Language :: Python :: 2.7
Classifier: Development Status :: 2 - Pre-Alpha
Classifier: Environment :: Other Environment
Classifier: Intended Audience :: Developers
Classifier: License :: OSI Approved :: MIT License
Classifier: Operating System :: OS Independent
Classifier: Topic :: Software Development :: Libraries :: Python Modules
Classifier: Topic :: Scientific/Engineering :: Artificial Intelligence
Classifier: Topic :: Scientific/Engineering :: Mathematics
